LICENSE
spartan/__init__.py
spartan/request.py
spartan_py-0.2.10.dist-info/LICENSE
spartan_py-0.2.10.dist-info/WHEEL
spartan_py-0.2.10.dist-info/METADATA
spartan_py-0.2.10.dist-info/RECORD
