Metadata-Version: 2.1
Name: spartan-py
Version: 0.2.10
Summary: Library for spartan protocol
Home-page: https://sr.ht/~hedy/spartan-py
License: MIT
Author: Hedy Li
Author-email: hedy@tilde.cafe
Requires-Python: >=3.7,<4.0
Classifier: License :: OSI Approved :: MIT License
Classifier: Programming Language :: Python :: 3
Classifier: Programming Language :: Python :: 3.7
Classifier: Programming Language :: Python :: 3.8
Classifier: Programming Language :: Python :: 3.9
Classifier: Topic :: Software Development :: Libraries :: Python Modules
Project-URL: Repository, https://sr.ht/~hedy/spartan-py
